CHANGES.txt
NOTES.txt
README.txt
setup.cfg
setup.py
src/dobbin/README.txt
src/dobbin/__init__.py
src/dobbin/database.py
src/dobbin/exc.py
src/dobbin/manager.py
src/dobbin/persistent.py
src/dobbin/utils.py
src/dobbin.egg-info/PKG-INFO
src/dobbin.egg-info/SOURCES.txt
src/dobbin.egg-info/dependency_links.txt
src/dobbin.egg-info/not-zip-safe
src/dobbin.egg-info/requires.txt
src/dobbin.egg-info/top_level.txt
src/dobbin/tests/__init__.py
src/dobbin/tests/base.py
src/dobbin/tests/test_benchmark.py
src/dobbin/tests/test_doctests.py
src/dobbin/tests/test_mvcc.py
src/dobbin/tests/test_persistent.py
src/dobbin/tests/test_persistentdict.py